[
  {
    "id": "550e8400-e29b-41d4-a716-446655440001",
    "username": "rotary_king_nz",
    "display_name": "Jake Thompson",
    "email": "jake@example.com",
    "password": "password123",
    "profile_image_url": "/profiles/daniel.jpg",
    "created_at": "2024-01-15T10:30:00Z",
    "updated_at": "2024-08-20T14:22:00Z"
  },
  {
    "id": "550e8400-e29b-41d4-a716-446655440002",
    "username": "skyline_sarah",
    "display_name": "Sarah Wilson",
    "email": "sarah@example.com",
    "password": "sarah2024",
    "profile_image_url": "/profiles/daniel.jpg",
    "created_at": "2024-02-03T09:15:00Z",
    "updated_at": "2024-08-18T16:45:00Z"
  },
  {
    "id": "550e8400-e29b-41d4-a716-446655440003",
    "username": "drift_master_chch",
    "display_name": "Marcus Chen",
    "email": "marcus@example.com",
    "password": "drift123",
    "profile_image_url": "/profiles/daniel.jpg",
    "created_at": "2024-01-28T13:20:00Z",
    "updated_at": "2024-08-19T11:10:00Z"
  },
  {
    "id": "550e8400-e29b-41d4-a716-446655440004",
    "username": "euro_enthusiast",
    "display_name": "Emma Rodriguez",
    "email": "emma@example.com",
    "password": "euro2024",
    "profile_image_url": "/profiles/daniel.jpg",
    "created_at": "2024-03-10T08:45:00Z",
    "updated_at": "2024-08-21T12:30:00Z"
  },
  {
    "id": "550e8400-e29b-41d4-a716-446655440005",
    "username": "stance_nation_wgtn",
    "display_name": "Tom Anderson",
    "email": "tom@example.com",
    "password": "stance123",
    "profile_image_url": "/profiles/daniel.jpg",
    "created_at": "2024-02-20T15:30:00Z",
    "updated_at": "2024-08-22T09:15:00Z"
  },
  {
    "id": "550e8400-e29b-41d4-a716-446655440006",
    "username": "jdm_legend",
    "display_name": "Priya Patel",
    "email": "priya@example.com",
    "password": "jdm2024",
    "profile_image_url": "/profiles/daniel.jpg",
    "created_at": "2024-01-05T11:45:00Z",
    "updated_at": "2024-08-20T17:20:00Z"
  },
  {
    "id": "550e8400-e29b-41d4-a716-446655440007",
    "username": "muscle_car_mike",
    "display_name": "Mike Johnson",
    "email": "mike@example.com",
    "password": "muscle123",
    "profile_image_url": "/profiles/daniel.jpg",
    "created_at": "2024-03-25T14:10:00Z",
    "updated_at": "2024-08-19T13:55:00Z"
  },
  {
    "id": "550e8400-e29b-41d4-a716-446655440008",
    "username": "track_day_amy",
    "display_name": "Amy Foster",
    "email": "amy@example.com",
    "password": "trackday2024",
    "profile_image_url": "/profiles/daniel.jpg",
    "created_at": "2024-02-14T16:25:00Z",
    "updated_at": "2024-08-21T10:40:00Z"
  },
  {
    "id": "550e8400-e29b-41d4-a716-446655440009",
    "username": "daniel_medcalf",
    "display_name": "Daniel Medcalf",
    "email": "daniel.m514@outlook.com",
    "password": "123",
    "profile_image_url": "/profiles/daniel.jpg",
    "created_at": "2024-08-25T12:00:00Z",
    "updated_at": "2024-08-25T12:00:00Z"
  },
  {
    "id": "550e8400-e29b-41d4-a716-446655440010",
    "username": "newcomer_nz",
    "display_name": "Alex Carter",
    "email": "alex.carter@example.com",
    "password": "123",
    "profile_image_url": "/profiles/daniel.jpg",
    "created_at": "2024-08-26T10:00:00Z",
    "updated_at": "2024-08-26T10:00:00Z"
  }
]
